promptsub/__init__.py
promptsub/errors.py
promptsub/prompt_api.py
promptsub/prompt_components/__init__.py
promptsub/prompt_components/base.py
promptsub/prompt_components/template.py
promptsub/prompt_components/variable.py
promptsub/special_chatacters.py
promptsub/types.py
promptsub-0.1.1.dist-info/LICENSE
promptsub-0.1.1.dist-info/METADATA
promptsub-0.1.1.dist-info/WHEEL
promptsub-0.1.1.dist-info/RECORD
