Metadata-Version: 2.1
Name: promptsub
Version: 0.1.1
Summary: Creating parametrized prompts for language models
License: MIT
Author: n-splv
Author-email: nick.maykr@gmail.com
Requires-Python: >=3.10,<4.0
Classifier: License :: OSI Approved :: MIT License
Classifier: Programming Language :: Python :: 3
Classifier: Programming Language :: Python :: 3.10
Classifier: Programming Language :: Python :: 3.11
Requires-Dist: attrs (>=23.2.0,<24.0.0)
